debug_utils.py
pydelog-1.0.0.dist-info/licenses/LICENSE
pydelog-1.0.0.dist-info/METADATA
pydelog-1.0.0.dist-info/WHEEL
pydelog-1.0.0.dist-info/top_level.txt
pydelog-1.0.0.dist-info/RECORD
