Metadata-Version: 2.4
Name: pydelog
Version: 1.0.0
Summary: Debug and logging utility with colored output and timers.
Author-email: Sajan Saji <isajansaji@gmail.com>
License: MIT
Project-URL: Homepage, https://github.com/sajansaji/pydelog
Requires-Python: >=3.8
License-File: LICENSE
Dynamic: license-file
